xerra/__init__.py
xerra/cli.py
xerra/download.py
xerra/importer.py
xerra-0.1.5.dist-info/METADATA
xerra-0.1.5.dist-info/WHEEL
xerra-0.1.5.dist-info/entry_points.txt
xerra-0.1.5.dist-info/RECORD
